setup.cfg
setup.py
sdh/__init__.py
sdh/curator/__init__.py
sdh/curator/client/__init__.py
sdh/curator/client/test.py
sdh_curator_py.egg-info/PKG-INFO
sdh_curator_py.egg-info/SOURCES.txt
sdh_curator_py.egg-info/dependency_links.txt
sdh_curator_py.egg-info/namespace_packages.txt
sdh_curator_py.egg-info/requires.txt
sdh_curator_py.egg-info/top_level.txt