Metadata-Version: 1.1
Name: sdh-curator-py
Version: 0.1.2
Summary: Python-based client to interact with the SDH Curator service
Home-page: https://github.com/smartdeveloperhub/sdh-curator-py
Author: Fernando Serena
Author-email: fernando.serena@centeropenmiddleware.com
License: Apache 2
Download-URL: https://github.com/smartdeveloperhub/sdh-curator-py/tarball/0.1.0-alpha1
Keywords: linked-data,ontology,curation
Platform: UNKNOWN
